skymapper/__init__.py
skymapper/mapper.py
skymapping-0.0.4.dist-info/LICENSE
skymapping-0.0.4.dist-info/METADATA
skymapping-0.0.4.dist-info/WHEEL
skymapping-0.0.4.dist-info/top_level.txt
skymapping-0.0.4.dist-info/RECORD
